tests/__init__.py
tests/conftest.py
tests/test_downloader.py
tests/test_url.py
yt_sdk/__init__.py
yt_sdk/downloader.py
yt_sdk/url.py
yt_sdk-0.0.3.dist-info/licenses/LICENSE
yt_sdk-0.0.3.dist-info/METADATA
yt_sdk-0.0.3.dist-info/WHEEL
yt_sdk-0.0.3.dist-info/top_level.txt
yt_sdk-0.0.3.dist-info/RECORD
