Metadata-Version: 2.4
Name: yt_sdk
Version: 0.0.3
Summary: Youtube SDK - Download video audio, etc...
Home-page: https://pypi.org/project/yt-sdk/
Author: Alejo Prieto Dávalos
Project-URL: Source, https://github.com/AlejoPrietoDavalos/yt-sdk/
Requires-Python: >=3.11
License-File: LICENSE
Requires-Dist: yt_dlp>=2025.1.26
Dynamic: author
Dynamic: description
Dynamic: description-content-type
Dynamic: home-page
Dynamic: license-file
Dynamic: project-url
Dynamic: requires-dist
Dynamic: requires-python
Dynamic: summary
